prometheux/__init__.py
prometheux/loader.py
prometheux/trainer.py
prometheux-0.0.6.dist-info/LICENSE
prometheux-0.0.6.dist-info/METADATA
prometheux-0.0.6.dist-info/WHEEL
prometheux-0.0.6.dist-info/top_level.txt
prometheux-0.0.6.dist-info/RECORD
