Metadata-Version: 2.1
Name: prometheux
Version: 0.0.6
Summary: Neurosymbolic Chain
Home-page: https://github.com/prometheuxresearch/neurosymbolicchain
Author: Prometheux Limited
Author-email: davben@prometheux.co.uk
Classifier: Programming Language :: Python :: 3
Classifier: License :: OSI Approved :: MIT License
Classifier: Operating System :: OS Independent
Requires-Python: >=3.7
License-File: LICENSE
Requires-Dist: pandas
Requires-Dist: flatdict
Requires-Dist: PyYAML
